api/__init__.py
api/main.py
api/models.py
api/routes.py
pdf_generator/__init__.py
pdf_generator/api_server.py
pdf_generator/cli.py
pdf_generator/config/__init__.py
pdf_generator/config/parser.py
pdf_generator/config/validator.py
pdf_generator/core/__init__.py
pdf_generator/core/cover_page.py
pdf_generator/core/elements.py
pdf_generator/core/generator.py
pdf_generator/core/header_footer.py
pdf_generator/core/page_template.py
pdf_generator/core/styles.py
pdf_generator/core/toc_generator.py
pdf_generator/data_sources/__init__.py
pdf_generator/data_sources/api_source.py
pdf_generator/data_sources/base.py
pdf_generator/data_sources/csv_source.py
pdf_generator/data_sources/database.py
pdf_generator/data_sources/json_source.py
pdf_generator/templates/cover_templates.py
pdf_generator/utils/__init__.py
pdf_generator/utils/chart_generator.py
pdf_generator/utils/page_numbers.py
pdf_report_generator-0.1.0.dist-info/licenses/LICENSE
pdf_report_generator-0.1.0.dist-info/METADATA
pdf_report_generator-0.1.0.dist-info/WHEEL
pdf_report_generator-0.1.0.dist-info/entry_points.txt
pdf_report_generator-0.1.0.dist-info/top_level.txt
pdf_report_generator-0.1.0.dist-info/RECORD
