Metadata-Version: 2.4
Name: pdf-report-generator
Version: 0.1.0
Summary: A flexible PDF report generator with JSON configuration support
Home-page: https://github.com/yourusername/pdf-report-generator
Author: PDF Report Team
License: MIT
Keywords: pdf,report,generator,reportlab,document
Classifier: Development Status :: 3 - Alpha
Classifier: Intended Audience :: Developers
Classifier: License :: OSI Approved :: MIT License
Classifier: Programming Language :: Python :: 3.9
Classifier: Programming Language :: Python :: 3.10
Classifier: Programming Language :: Python :: 3.11
Classifier: Programming Language :: Python :: 3.12
Requires-Python: >=3.9
License-File: LICENSE
Requires-Dist: reportlab>=4.0.0
Requires-Dist: Pillow>=10.0.0
Requires-Dist: pandas>=2.0.0
Requires-Dist: matplotlib>=3.7.0
Requires-Dist: Jinja2>=3.0.0
Requires-Dist: openpyxl>=3.0.0
Requires-Dist: requests>=2.28.0
Requires-Dist: SQLAlchemy>=2.0.0
Provides-Extra: api
Requires-Dist: fastapi>=0.100.0; extra == "api"
Requires-Dist: uvicorn[standard]>=0.23.0; extra == "api"
Requires-Dist: python-multipart>=0.0.6; extra == "api"
Requires-Dist: pydantic>=2.0.0; extra == "api"
Provides-Extra: dev
Requires-Dist: pytest>=7.0.0; extra == "dev"
Requires-Dist: black>=23.0.0; extra == "dev"
Requires-Dist: flake8>=6.0.0; extra == "dev"
Provides-Extra: all
Requires-Dist: fastapi>=0.100.0; extra == "all"
Requires-Dist: uvicorn[standard]>=0.23.0; extra == "all"
Requires-Dist: python-multipart>=0.0.6; extra == "all"
Requires-Dist: pydantic>=2.0.0; extra == "all"
Requires-Dist: pytest>=7.0.0; extra == "all"
Requires-Dist: black>=23.0.0; extra == "all"
Requires-Dist: flake8>=6.0.0; extra == "all"
Dynamic: home-page
Dynamic: license-file
Dynamic: requires-python
